tripleuni/ChatBot.py
tripleuni/TripleClient.py
tripleuni/__init__.py
tripleuni-0.4.2.dist-info/LICENSE.txt
tripleuni-0.4.2.dist-info/METADATA
tripleuni-0.4.2.dist-info/WHEEL
tripleuni-0.4.2.dist-info/top_level.txt
tripleuni-0.4.2.dist-info/RECORD
