Metadata-Version: 2.1
Name: tripleuni
Version: 0.4.2
Summary: python library for tripleuni
Author-email: Zilong ZHOU <zzl0712@outlook.com>
Maintainer-email: Zilong ZHOU <zzl0712@outlook.com>
License: Copyright (c) 2016 The Python Packaging Authority (PyPA)
Keywords: web,tripleuni
Classifier: Development Status :: 3 - Alpha
Classifier: Intended Audience :: Developers
Classifier: Topic :: Software Development :: Build Tools
Classifier: License :: OSI Approved :: MIT License
Classifier: Programming Language :: Python :: 3
Classifier: Programming Language :: Python :: 3.7
Classifier: Programming Language :: Python :: 3.8
Classifier: Programming Language :: Python :: 3.9
Classifier: Programming Language :: Python :: 3.10
Classifier: Programming Language :: Python :: 3.11
Classifier: Programming Language :: Python :: 3 :: Only
Requires-Python: >=3.7
License-File: LICENSE.txt
Requires-Dist: requests
Provides-Extra: dev
Requires-Dist: check-manifest; extra == "dev"
Provides-Extra: test
Requires-Dist: coverage; extra == "test"
